my_pet_1_api_client/__init__.py
my_pet_1_api_client/api_client.py
my_pet_1_api_client/api_response.py
my_pet_1_api_client/configuration.py
my_pet_1_api_client/exceptions.py
my_pet_1_api_client/py.typed
my_pet_1_api_client/rest.py
my_pet_1_api_client/api/__init__.py
my_pet_1_api_client/api/pet_api.py
my_pet_1_api_client/api/store_api.py
my_pet_1_api_client/api/user_api.py
my_pet_1_api_client/models/__init__.py
my_pet_1_api_client/models/address.py
my_pet_1_api_client/models/api_response.py
my_pet_1_api_client/models/category.py
my_pet_1_api_client/models/customer.py
my_pet_1_api_client/models/order.py
my_pet_1_api_client/models/pet.py
my_pet_1_api_client/models/tag.py
my_pet_1_api_client/models/user.py
my_pet_1_api_client-1.0.0.dist-info/METADATA
my_pet_1_api_client-1.0.0.dist-info/WHEEL
my_pet_1_api_client-1.0.0.dist-info/top_level.txt
my_pet_1_api_client-1.0.0.dist-info/RECORD
